{
  "current": "v0.0.8",
  "history": [
    {
      "version": "v0.0.6",
      "date": "26/06/2026",
      "type": "patch",
      "changelog": "Actualizacion de mantenimiento",
      "tag": "Ulises_Uzcategui-v0.0.6"
    },
    {
      "version": "v0.0.7",
      "date": "26/06/2026",
      "type": "patch",
      "changelog": "Actualizacion de mantenimiento",
      "tag": "Ulises_Uzcategui-v0.0.7"
    },
    {
      "version": "v0.0.8",
      "date": "26/06/2026",
      "type": "patch",
      "changelog": "Actualizacion de mantenimiento",
      "tag": "Ulises_Uzcategui-v0.0.8"
    }
  ]
}